second_test/__init__.py
second_test/empty.py
second_test-0.1.2.dist-info/METADATA
second_test-0.1.2.dist-info/WHEEL
second_test-0.1.2.dist-info/RECORD
